LICENSE
README.md
setup.py
tmkit/Path.py
tmkit/SeqNetRR.py
tmkit/__init__.py
tmkit/cath.py
tmkit/collate.py
tmkit/edge.py
tmkit/feature.py
tmkit/mapping.py
tmkit/msa.py
tmkit/mut.py
tmkit/pl.py
tmkit/ppi.py
tmkit/qc.py
tmkit/rrc.py
tmkit/seq.py
tmkit/topo.py
tmkit/vs.py
tmkit/base/PDB.py
tmkit/base/Position.py
tmkit/base/__init__.py
tmkit/chain/Collate.py
tmkit/chain/CollateBatch.py
tmkit/chain/PDB.py
tmkit/chain/__init__.py
tmkit/channel/Workbench.py
tmkit/channel/__init__.py
tmkit/contact/Evaluator.py
tmkit/contact/Reader.py
tmkit/contact/__init__.py
tmkit/db/Connectivity.py
tmkit/db/Reader.py
tmkit/db/__init__.py
tmkit/db/biogrid/Reader.py
tmkit/db/biogrid/__init__.py
tmkit/db/cath/Reader.py
tmkit/db/cath/__init__.py
tmkit/db/construct/Network.py
tmkit/db/construct/__init__.py
tmkit/db/intact/Reader.py
tmkit/db/intact/__init__.py
tmkit/db/muthtp/Reader.py
tmkit/db/muthtp/__init__.py
tmkit/db/predmuthtp/Reader.py
tmkit/db/predmuthtp/__init__.py
tmkit/feature/HelixSurface.py
tmkit/feature/__init__.py
tmkit/feature/lips/__init__.py
tmkit/id/Fasta.py
tmkit/id/Mapping.py
tmkit/id/PDB.py
tmkit/id/__init__.py
tmkit/interface/Tool.py
tmkit/interface/Topology.py
tmkit/interface/__init__.py
tmkit/name/Mapping.py
tmkit/name/__init__.py
tmkit/position/__init__.py
tmkit/position/scenario/Segment.py
tmkit/position/scenario/Separation.py
tmkit/position/scenario/__init__.py
tmkit/retrieve/MSA.py
tmkit/retrieve/PDB.py
tmkit/retrieve/XML.py
tmkit/retrieve/__init__.py
tmkit/seqnetrr/Compare.py
tmkit/seqnetrr/Controller.py
tmkit/seqnetrr/Path.py
tmkit/seqnetrr/Plot.py
tmkit/seqnetrr/__init__.py
tmkit/seqnetrr/combo/Length.py
tmkit/seqnetrr/combo/Param.py
tmkit/seqnetrr/combo/Position.py
tmkit/seqnetrr/combo/Separation.py
tmkit/seqnetrr/combo/__init__.py
tmkit/seqnetrr/graph/Bipartite.py
tmkit/seqnetrr/graph/Cumulative.py
tmkit/seqnetrr/graph/Unipartite.py
tmkit/seqnetrr/graph/__init__.py
tmkit/seqnetrr/net/Reader.py
tmkit/seqnetrr/net/__init__.py
tmkit/seqnetrr/sequence/Fasta.py
tmkitx.egg-info/PKG-INFO
tmkitx.egg-info/SOURCES.txt
tmkitx.egg-info/dependency_links.txt
tmkitx.egg-info/requires.txt
tmkitx.egg-info/top_level.txt